ipythonblocks/__init__.py
ipythonblocks/ipythonblocks.py
ipythonblocks-1.9.1.dist-info/LICENSE.txt
ipythonblocks-1.9.1.dist-info/METADATA
ipythonblocks-1.9.1.dist-info/WHEEL
ipythonblocks-1.9.1.dist-info/top_level.txt
ipythonblocks-1.9.1.dist-info/RECORD
