Metadata-Version: 2.1
Name: ipythonblocks
Version: 1.9.1
Summary: Practice Python with colored grids in the IPython Notebook
Home-page: https://github.com/jiffyclub/ipythonblocks/
Author: Matt Davis
Author-email: jiffyclub@gmail.com
Classifier: License :: OSI Approved :: MIT License
Classifier: Programming Language :: Python
Classifier: Programming Language :: Python :: 2
Classifier: Programming Language :: Python :: 2.7
Classifier: Programming Language :: Python :: 3
Classifier: Intended Audience :: Education
Classifier: Topic :: Education
License-File: LICENSE.txt
Requires-Dist: ipython>=4.0
Requires-Dist: notebook>=4.0
Requires-Dist: requests>=1.0
